fakegrpc/__init__.py
fakegrpc/api/grpc/__init__.py
fakegrpc/api/grpc/health/__init__.py
fakegrpc/api/grpc/health/v1/__init__.py
fakegrpc/server/__init__.py
fakegrpc/server/command.py
fakegrpc/server/e2etest.py
fakegrpc/server/grpc.py
fakegrpc/server/port.py
fakegrpc/server/fakegrpc/__init__.py
fakegrpc/server/fakegrpc/fake_server_generator.py
fakegrpc/server/fakegrpc/fake_server_stub.py
fakegrpc/server/fakegrpc/fake_server_template.py
fakegrpc/server/fakegrpc/server.py
fakegrpc/tid/__init__.py
fakegrpc/tid/grpc_propagator.py
fakegrpc/tid/tid.py
fakegrpc-0.1.4.dist-info/METADATA
fakegrpc-0.1.4.dist-info/WHEEL
fakegrpc-0.1.4.dist-info/licenses/LICENSE
fakegrpc-0.1.4.dist-info/RECORD
