Metadata-Version: 2.4
Name: fakegrpc
Version: 0.1.4
Summary: A E2E testing framework for services based on gRPC
Author-email: Shota Kono <dqx1005@gmail.com>
License: MIT
License-File: LICENSE
Requires-Python: >=3.12
Requires-Dist: betterproto[compiler]==2.0.0b7
Requires-Dist: grpclib==0.4.7
Requires-Dist: python-dotenv
